roguewavespectrum/__init__.py
roguewavespectrum/_directions.py
roguewavespectrum/_factory_methods.py
roguewavespectrum/_geospatial.py
roguewavespectrum/_operations.py
roguewavespectrum/_partitioning.py
roguewavespectrum/_physical_constants.py
roguewavespectrum/_physics.py
roguewavespectrum/_spectrum.py
roguewavespectrum/_spline_interpolation.py
roguewavespectrum/_time.py
roguewavespectrum/_timeseries.py
roguewavespectrum/_variable_names.py
roguewavespectrum/parametric.py
roguewavespectrum/_estimators/__init__.py
roguewavespectrum/_estimators/estimate.py
roguewavespectrum/_estimators/mem.py
roguewavespectrum/_estimators/mem2.py
roguewavespectrum/spotter/__init__.py
roguewavespectrum/spotter/_spotter_extrapolate_tail.py
roguewavespectrum/spotter/_spotter_post_processing.py
roguewavespectrum/spotter/_spotter_sdcard_data.py
roguewavespectrum/spotter/_spotter_time_integration.py
roguewavespectrum/spotter/_spotter_wavefleet_api.py
roguewavespectrum-0.2.21.dist-info/LICENSE
roguewavespectrum-0.2.21.dist-info/METADATA
roguewavespectrum-0.2.21.dist-info/WHEEL
roguewavespectrum-0.2.21.dist-info/top_level.txt
roguewavespectrum-0.2.21.dist-info/RECORD
